django_dictmessages-1.0.0.dist-info/WHEEL
django_dictmessages-1.0.0.dist-info/metadata.json
django_dictmessages-1.0.0.dist-info/METADATA
django_dictmessages-1.0.0.dist-info/top_level.txt
django_dictmessages-1.0.0.dist-info/RECORD
django_dictmessages-1.0.0.dist-info/zip-safe
django_dictmessages-1.0.0.dist-info/DESCRIPTION.rst
dictmessages/messages.py
dictmessages/api.py
dictmessages/models.py
dictmessages/__init__.py
