Metadata-Version: 2.0
Name: django-dictmessages
Version: 1.0.0
Summary: django.contrib.messages wrapper allowing pre-rendering of message dictionaries
Home-page: https://bitbucket.org/mhurt/django-dictmessages
Author: Mike Hurt
Author-email: mike@mhtechnical.net
License: MIT
Keywords: django messages dictionary template utility
Platform: UNKNOWN
Classifier: Development Status :: 3 - Alpha
Classifier: Environment :: Web Environment
Classifier: Framework :: Django
Classifier: Intended Audience :: Developers
Classifier: License :: OSI Approved :: MIT License
Classifier: Operating System :: OS Independent
Classifier: Programming Language :: Python
Classifier: Topic :: Internet :: WWW/HTTP :: Dynamic Content
Requires-Dist: Django (>=1.4.2)
